ccDemo/__init__.py
ccDemo/ccMain.py
ccDemo/convexclustering.py
ccDemo-0.1.2.dist-info/METADATA
ccDemo-0.1.2.dist-info/WHEEL
ccDemo-0.1.2.dist-info/top_level.txt
ccDemo-0.1.2.dist-info/RECORD
