Metadata-Version: 2.1
Name: ccDemo
Version: 0.1.2
Summary: Demo for convex clustering
Home-page: https://github.com/canhhao/convexclustering
Author: Canh Hao Nguyen
Author-email: canhhao@gmail.com
License: MIT
Keywords: convex clustering
Platform: UNKNOWN
Classifier: Development Status :: 3 - Alpha
Classifier: Intended Audience :: Developers
Classifier: License :: OSI Approved :: MIT License
Classifier: Programming Language :: Python :: 3
Requires-Dist: pandas
Requires-Dist: numpy
Requires-Dist: matplotlib
Requires-Dist: sklearn
